cvu/__init__.py
cvu/detector/__init__.py
cvu/detector/configs.py
cvu/detector/prediction.py
cvu/detector/predictions.py
cvu/detector/yolov5/__init__.py
cvu/detector/yolov5/core.py
cvu/detector/yolov5/backends/__init__.py
cvu/detector/yolov5/backends/common.py
cvu/detector/yolov5/backends/yolov5_onnx.py
cvu/detector/yolov5/backends/yolov5_tensorflow.py
cvu/detector/yolov5/backends/yolov5_tensorrt.py
cvu/detector/yolov5/backends/yolov5_tflite.py
cvu/detector/yolov5/backends/yolov5_torch.py
cvu/detector/yolov5/backends/weights/onnx_weights.json
cvu/detector/yolov5/backends/weights/tensorflow_weights.json
cvu/detector/yolov5/backends/weights/tensorrt_weights.json
cvu/detector/yolov5/backends/weights/tflite_weights.json
cvu/detector/yolov5/backends/weights/torch_weights.json
cvu/interface/__init__.py
cvu/interface/core.py
cvu/interface/model.py
cvu/interface/predictions.py
cvu/interface/sink.py
cvu/interface/source.py
cvu/postprocess/__init__.py
cvu/postprocess/bbox.py
cvu/postprocess/backend_tf/__init__.py
cvu/postprocess/backend_tf/nms/__init__.py
cvu/postprocess/backend_tf/nms/yolov5.py
cvu/postprocess/backend_torch/__init__.py
cvu/postprocess/backend_torch/nms/__init__.py
cvu/postprocess/backend_torch/nms/yolov5.py
cvu/postprocess/nms/__init__.py
cvu/postprocess/nms/basic.py
cvu/postprocess/nms/yolov5.py
cvu/preprocess/__init__.py
cvu/preprocess/image/__init__.py
cvu/preprocess/image/general.py
cvu/preprocess/image/letterbox.py
cvu/utils/__init__.py
cvu/utils/bbox.py
cvu/utils/colors.py
cvu/utils/draw.py
cvu/utils/general.py
cvu/utils/google_utils.py
cvu/utils/backend/__init__.py
cvu/utils/backend/backend_config.json
cvu/utils/backend/package.py
cvu/utils/backend/setup_onnx.py
cvu/utils/backend/setup_tensorflow.py
cvu/utils/backend/setup_tensorrt.py
cvu/utils/backend/setup_tflite.py
cvu/utils/backend/setup_torch.py
cvu/utils/backend_onnx/__init__.py
cvu/utils/backend_onnx/convert_to_onnx.py
cvu/utils/backend_tensorrt/__init__.py
cvu_python-0.0.2.dist-info/LICENSE
cvu_python-0.0.2.dist-info/METADATA
cvu_python-0.0.2.dist-info/WHEEL
cvu_python-0.0.2.dist-info/top_level.txt
cvu_python-0.0.2.dist-info/RECORD
