Metadata-Version: 2.1
Name: cvu-python
Version: 0.0.2
Summary: Computer Vision deployment tools for dummies and experts.
Home-page: https://github.com/BlueMirrors/cvu
Author: BlueMirrors
Author-email: contact.bluemirrors@gmail.com
License: Apache Software License v2.0
Classifier: License :: OSI Approved :: Apache Software License
Classifier: Programming Language :: Python :: 3
Classifier: Programming Language :: Python :: 3.6
Classifier: Programming Language :: Python :: 3.7
Classifier: Programming Language :: Python :: 3.8
Classifier: Programming Language :: Python :: 3.9
License-File: LICENSE
Requires-Dist: opencv-python
Requires-Dist: vidsz
Requires-Dist: numpy
Requires-Dist: gdown
